{"coord":{"lon":32.8543,"lat":39.9199},"weather":[{"id":500,"main":"Rain","description":"hafif yağmur","icon":"10n"}],"base":"stations","main":{"temp":7.35,"feels_like":5.24,"temp_min":5.51,"temp_max":7.36,"pressure":1006,"humidity":87,"sea_level":1006,"grnd_level":884},"visibility":10000,"wind":{"speed":3.13,"deg":200,"gust":5.81},"rain":{"1h":0.22},"clouds":{"all":100},"dt":1770416237,"sys":{"type":2,"id":267643,"country":"TR","sunrise":1770439876,"sunset":1770477252},"timezone":10800,"id":323786,"name":"Ankara","cod":200}