{"coord":{"lon":-7.4909,"lat":39.8222},"weather":[{"id":600,"main":"Snow","description":"neve fraca","icon":"13n"}],"base":"stations","main":{"temp":1.81,"feels_like":-1.08,"temp_min":1.81,"temp_max":1.81,"pressure":1009,"humidity":93,"sea_level":1009,"grnd_level":976},"visibility":10000,"wind":{"speed":2.72,"deg":238,"gust":6.52},"snow":{"1h":0.1},"clouds":{"all":60},"dt":1770411807,"sys":{"country":"PT","sunrise":1770363204,"sunset":1770400481},"timezone":0,"id":2269514,"name":"Castelo Branco","cod":200}