{"coord":{"lon":-7.4909,"lat":39.8222},"weather":[{"id":803,"main":"Clouds","description":"nuvens quebradas","icon":"04n"}],"base":"stations","main":{"temp":1.98,"feels_like":-1.16,"temp_min":1.98,"temp_max":1.98,"pressure":1011,"humidity":94,"sea_level":1011,"grnd_level":978},"visibility":10000,"wind":{"speed":3.05,"deg":224,"gust":8.63},"clouds":{"all":52},"dt":1770421738,"sys":{"country":"PT","sunrise":1770363204,"sunset":1770400481},"timezone":0,"id":2269514,"name":"Castelo Branco","cod":200}