{"coord":{"lon":-7.4909,"lat":39.8222},"weather":[{"id":802,"main":"Clouds","description":"parçalı az bulutlu","icon":"03d"}],"base":"stations","main":{"temp":16.7,"feels_like":15.29,"temp_min":16.7,"temp_max":16.7,"pressure":1013,"humidity":33,"sea_level":1013,"grnd_level":981},"visibility":10000,"wind":{"speed":5.08,"deg":299,"gust":5.63},"clouds":{"all":39},"dt":1777904969,"sys":{"country":"PT","sunrise":1777872415,"sunset":1777922790},"timezone":3600,"id":2269514,"name":"Castelo Branco","cod":200}