{"coord":{"lon":32.8543,"lat":39.9199},"weather":[{"id":800,"main":"Clear","description":"céu limpo","icon":"01d"}],"base":"stations","main":{"temp":17.91,"feels_like":16.49,"temp_min":17.91,"temp_max":19.51,"pressure":1007,"humidity":28,"sea_level":1007,"grnd_level":887},"visibility":10000,"wind":{"speed":3.42,"deg":231,"gust":5.42},"clouds":{"all":0},"dt":1778947409,"sys":{"type":2,"id":2108472,"country":"TR","sunrise":1778898781,"sunset":1778950624},"timezone":10800,"id":323786,"name":"Ancara","cod":200}