{"coord":{"lon":-7.4909,"lat":39.8222},"weather":[{"id":803,"main":"Clouds","description":"parçalı bulutlu","icon":"04d"}],"base":"stations","main":{"temp":30.54,"feels_like":28.56,"temp_min":30.54,"temp_max":30.54,"pressure":1018,"humidity":14,"sea_level":1018,"grnd_level":986},"visibility":10000,"wind":{"speed":2.56,"deg":159,"gust":2.94},"clouds":{"all":65},"dt":1779460384,"sys":{"country":"PT","sunrise":1779426585,"sunset":1779479028},"timezone":3600,"id":2269514,"name":"Castelo Branco","cod":200}