{"coord":{"lon":32.8543,"lat":39.9199},"weather":[{"id":500,"main":"Rain","description":"chuva fraca","icon":"10d"}],"base":"stations","main":{"temp":5.11,"feels_like":3.26,"temp_min":4.51,"temp_max":5.11,"pressure":1009,"humidity":89,"sea_level":1009,"grnd_level":888},"visibility":4778,"wind":{"speed":2.24,"deg":328,"gust":2.68},"rain":{"1h":0.35},"clouds":{"all":100},"dt":1776915956,"sys":{"type":2,"id":267643,"country":"TR","sunrise":1776913174,"sunset":1776962038},"timezone":10800,"id":323786,"name":"Ancara","cod":200}